ApacheZeppelin072ZhongwenWendang/README.md
ApacheZeppelin072ZhongwenWendang/__init__.py
ApacheZeppelin072ZhongwenWendang/__main__.py
ApacheZeppelin072ZhongwenWendang/file.epub
ApacheZeppelin072ZhongwenWendang/index.html
ApacheZeppelin072ZhongwenWendang/css/__init__.py
ApacheZeppelin072ZhongwenWendang/css/annotations.css
ApacheZeppelin072ZhongwenWendang/css/main.css
ApacheZeppelin072ZhongwenWendang/css/normalize.css
ApacheZeppelin072ZhongwenWendang/css/popup.css
ApacheZeppelin072ZhongwenWendang/font/__init__.py
ApacheZeppelin072ZhongwenWendang/font/fontello.eot
ApacheZeppelin072ZhongwenWendang/font/fontello.svg
ApacheZeppelin072ZhongwenWendang/font/fontello.ttf
ApacheZeppelin072ZhongwenWendang/font/fontello.woff
ApacheZeppelin072ZhongwenWendang/img/__init__.py
ApacheZeppelin072ZhongwenWendang/img/annotator-glyph-sprite.png
ApacheZeppelin072ZhongwenWendang/img/annotator-icon-sprite.png
ApacheZeppelin072ZhongwenWendang/img/apple-touch-icon.png
ApacheZeppelin072ZhongwenWendang/img/cancelfullscreen.png
ApacheZeppelin072ZhongwenWendang/img/close.png
ApacheZeppelin072ZhongwenWendang/img/fullscreen.png
ApacheZeppelin072ZhongwenWendang/img/loader.gif
ApacheZeppelin072ZhongwenWendang/img/menu-icon.png
ApacheZeppelin072ZhongwenWendang/img/save.png
ApacheZeppelin072ZhongwenWendang/img/saved.png
ApacheZeppelin072ZhongwenWendang/img/settings-s.png
ApacheZeppelin072ZhongwenWendang/img/settings.png
ApacheZeppelin072ZhongwenWendang/img/star.png
ApacheZeppelin072ZhongwenWendang/js/__init__.py
ApacheZeppelin072ZhongwenWendang/js/epub.js
ApacheZeppelin072ZhongwenWendang/js/epub.min.js
ApacheZeppelin072ZhongwenWendang/js/epub.min.map
ApacheZeppelin072ZhongwenWendang/js/hooks.min.js
ApacheZeppelin072ZhongwenWendang/js/hooks.min.map
ApacheZeppelin072ZhongwenWendang/js/reader.js
ApacheZeppelin072ZhongwenWendang/js/reader.js.map
ApacheZeppelin072ZhongwenWendang/js/reader.min.js
ApacheZeppelin072ZhongwenWendang/js/reader.min.map
ApacheZeppelin072ZhongwenWendang/js/hooks/__init__.py
apache_zeppelin_0_7_2_zhongwen_wendang-2024.3.2.0.dist-info/METADATA
apache_zeppelin_0_7_2_zhongwen_wendang-2024.3.2.0.dist-info/WHEEL
apache_zeppelin_0_7_2_zhongwen_wendang-2024.3.2.0.dist-info/entry_points.txt
apache_zeppelin_0_7_2_zhongwen_wendang-2024.3.2.0.dist-info/top_level.txt
apache_zeppelin_0_7_2_zhongwen_wendang-2024.3.2.0.dist-info/RECORD
